setup.py
dist_gaus_bino/Binomialdistribution.py
dist_gaus_bino/Gaussiandistribution.py
dist_gaus_bino/Generaldistribution.py
dist_gaus_bino/__init__.py
dist_gaus_bino.egg-info/PKG-INFO
dist_gaus_bino.egg-info/SOURCES.txt
dist_gaus_bino.egg-info/dependency_links.txt
dist_gaus_bino.egg-info/not-zip-safe
dist_gaus_bino.egg-info/top_level.txt