Metadata-Version: 2.1
Name: dist-gaus-bino
Version: 0.1
Summary: Gaussian distributions
